trade/__init__.py
trade/main.py
trade/calendar/__init__.py
trade/calendar/calendar_data.py
trade/calendar/calendar_tool.py
trade/exchange/__init__.py
trade/exchange/api_config.py
trade/exchange/market.py
trade/exchange/yf.py
trade/nse/__init__.py
trade/nse/indices/__init__.py
trade/nse/indices/nse_all_indices.py
trade/nse/indices/nse_index.py
trade/nse/nse_configs/__init__.py
trade/nse/nse_configs/nse_config.py
trade/nse/nse_configs/nse_fno.py
trade/nse/nse_configs/nse_indices_config.py
trade/nse/nse_generics/__init__.py
trade/nse/nse_generics/all_data_generics.py
trade/nse/nse_generics/data_generics.py
trade/nse/stocks/__init__.py
trade/nse/stocks/nse_all_stocks.py
trade/nse/stocks/nse_stock.py
trade/reports/__init__.py
trade/reports/index_report.py
trade/reports/stock_reports.py
trade/strategies/__init__.py
trade/strategies/scan/__init__.py
trade/strategies/scan/scans.py
trade/strategies/scan/master/__init__.py
trade/strategies/scan/master/strategies_generic.py
trade/strategies/scan/master/swing_strategies.py
trade/strategies/scan/swings/__init__.py
trade/strategies/scan/swings/big_bang_volume.py
trade/technicals/__init__.py
trade/technicals/indicators/__init__.py
trade/technicals/indicators/generic_indicator.py
trade/technicals/indicators/moving_averges.py
trade/technicals/indicators/rsi.py
trade/technicals/indicators/pivot_points/__init__.py
trade/technicals/indicators/pivot_points/pivot_points.py
trade/technicals/indicators/pivot_points/standard_pivot_points.py
trade/technicals/option_chain/__init__.py
trade/technicals/option_chain/generic_option_chain.py
trade/technicals/option_chain/index_option_chain.py
trade/technicals/option_chain/option_chain.py
trade/technicals/option_chain/stock_option_chain.py
trade/utils/__init__.py
trade/utils/df_market_utils.py
trade/utils/html_parsing.py
trade/utils/log_configurator.py
trade/utils/network_tools.py
trade/utils/op_utils.py
trade/utils/singleton_meta.py
trade/utils/utility_enabler.py
trade/utils/notify/__init__.py
market_generic-0.5.0.dist-info/METADATA
market_generic-0.5.0.dist-info/WHEEL
market_generic-0.5.0.dist-info/top_level.txt
market_generic-0.5.0.dist-info/RECORD
