Metadata-Version: 2.1
Name: market-generic
Version: 0.5.0
Summary: A Generic Python Package for Stock Market Analysis and Trading
Home-page: https://github.com/sharmasourab93/market-generic
Author: Sourab S Sharma
Author-email: sharmasourab93@gmail.com
Keywords: Market,Trade,Analysis
Requires-Dist: black ==24.4.2
Requires-Dist: isort ==5.13.2
Requires-Dist: numpy ==1.26.4
Requires-Dist: pandas ==2.2.2
Requires-Dist: dateutils ==0.6.12
Requires-Dist: gspread ==6.1.0
Requires-Dist: python-telegram-bot ==21.1.1
Requires-Dist: yfinance ==0.2.38
Requires-Dist: requests ~=2.31.0
Requires-Dist: pytz ~=2024.1
Requires-Dist: setuptools ~=69.5.1
Requires-Dist: beautifulsoup4 ==4.12.3
Requires-Dist: openpyxl ==3.1.2
Requires-Dist: pandas-ta ==0.3.14b0
Requires-Dist: tabulate ==0.9.0
